celestia_node/__init__.py
celestia_node/constants.py
celestia_node/dataclasses.py
celestia_node/blob/__init__.py
celestia_node/blob/blob.py
celestia_node/blob/sample.py
celestia_node/blob/tests.py
celestia_node/blob/types.py
celestia_node/das/__init__.py
celestia_node/das/sample.py
celestia_node/das/tests.py
celestia_node/das/types.py
celestia_node-0.0.4.dist-info/LICENSE.md
celestia_node-0.0.4.dist-info/METADATA
celestia_node-0.0.4.dist-info/WHEEL
celestia_node-0.0.4.dist-info/top_level.txt
celestia_node-0.0.4.dist-info/RECORD
