Metadata-Version: 2.1
Name: celestia-node
Version: 0.0.4
Summary: Celestia Node Python SDK
Home-page: https://github.com/grumpyp/celestia-node-client-py
Author: Patrick Gerard
Author-email: hallo@patrickgerard.de
Keywords: blockchain celestia node sdk client
Classifier: License :: OSI Approved :: MIT License
Classifier: Programming Language :: Python
Classifier: Programming Language :: Python :: 3
Requires-Python: >=3.8
License-File: LICENSE.md
Requires-Dist: requests >=2.26.0
Requires-Dist: loguru >=0.7.0
